<annotation><folder>util/images</folder><filename>clock-000207.png</filename><segmented>0</segmented><size><width>217</width><height>233</height><depth>3</depth></size><object><name>alarm_clock</name><pose>Unspecified</pose><truncated>0</truncated><difficult>0</difficult><bndbox><xmin>32</xmin><ymin>2</ymin><xmax>176</xmax><ymax>187</ymax></bndbox></object><object><name>alarm_clock</name><pose>Unspecified</pose><truncated>0</truncated><difficult>0</difficult><bndbox><xmin>40</xmin><ymin>2</ymin><xmax>176</xmax><ymax>187</ymax></bndbox></object></annotation>